jaxhps/__init__.py
jaxhps/_adaptive_discretization_2D.py
jaxhps/_adaptive_discretization_3D.py
jaxhps/_build_solver.py
jaxhps/_device_config.py
jaxhps/_discretization_tree.py
jaxhps/_discretization_tree_operations_2D.py
jaxhps/_discretization_tree_operations_3D.py
jaxhps/_domain.py
jaxhps/_grid_creation_2D.py
jaxhps/_grid_creation_3D.py
jaxhps/_interpolation_methods.py
jaxhps/_leaf_recomp.py
jaxhps/_pdeproblem.py
jaxhps/_precompute_operators_2D.py
jaxhps/_precompute_operators_3D.py
jaxhps/_solve.py
jaxhps/_subtree_recomp.py
jaxhps/_utils.py
jaxhps/down_pass/__init__.py
jaxhps/down_pass/_adaptive_2D_DtN.py
jaxhps/down_pass/_adaptive_3D_DtN.py
jaxhps/down_pass/_uniform_2D_DtN.py
jaxhps/down_pass/_uniform_2D_ItI.py
jaxhps/down_pass/_uniform_3D_DtN.py
jaxhps/local_solve/__init__.py
jaxhps/local_solve/_adaptive_2D_DtN.py
jaxhps/local_solve/_adaptive_3D_DtN.py
jaxhps/local_solve/_nosource_uniform_2D_DtN.py
jaxhps/local_solve/_nosource_uniform_2D_ItI.py
jaxhps/local_solve/_uniform_2D_DtN.py
jaxhps/local_solve/_uniform_2D_ItI.py
jaxhps/local_solve/_uniform_3D_DtN.py
jaxhps/merge/__init__.py
jaxhps/merge/_adaptive_2D_DtN.py
jaxhps/merge/_adaptive_3D_DtN.py
jaxhps/merge/_nosource_uniform_2D_DtN.py
jaxhps/merge/_nosource_uniform_2D_ItI.py
jaxhps/merge/_schur_complement.py
jaxhps/merge/_uniform_2D_DtN.py
jaxhps/merge/_uniform_2D_ItI.py
jaxhps/merge/_uniform_3D_DtN.py
jaxhps/merge/_utils_adaptive_2D_DtN.py
jaxhps/merge/_utils_adaptive_3D_DtN.py
jaxhps/quadrature/__init__.py
jaxhps/quadrature/_differentiation.py
jaxhps/quadrature/_discretization.py
jaxhps/quadrature/_interpolation.py
jaxhps/quadrature/_utils.py
jaxhps/up_pass/__init__.py
jaxhps/up_pass/_uniform_2D_DtN.py
jaxhps/up_pass/_uniform_2D_ItI.py
jaxhps-0.2.dist-info/licenses/LICENSE
jaxhps-0.2.dist-info/METADATA
jaxhps-0.2.dist-info/WHEEL
jaxhps-0.2.dist-info/top_level.txt
jaxhps-0.2.dist-info/RECORD
