Metadata-Version: 2.4
Name: jaxhps
Version: 0.2
Summary: An elliptic PDE solver built with machine learning in mind
Author-email: Owen Melia <owenjmelia@gmail.com>
License-Expression: MIT
Project-URL: homepage, https://github.com/meliao/jaxhps
Project-URL: documentation, https://jaxhps.readthedocs.io/en/latest/
Keywords: jax,PDE,elliptic,HPS,spectral,numerical analysis
Classifier: Development Status :: 4 - Beta
Classifier: Intended Audience :: Science/Research
Classifier: Programming Language :: Python :: 3
Classifier: Topic :: Scientific/Engineering :: Mathematics
Requires-Python: >=3.10
License-File: LICENSE
Requires-Dist: scipy>=1.14
Requires-Dist: jax>=0.4
Provides-Extra: dev
Requires-Dist: pytest>=7.4.4; extra == "dev"
Requires-Dist: Sphinx>=8.1.3; extra == "dev"
Requires-Dist: sphinx-rtd-theme>=3.0.2; extra == "dev"
Requires-Dist: pre_commit>=4.2.0; extra == "dev"
Requires-Dist: ruff>=0.11.2; extra == "dev"
Requires-Dist: matplotlib>=3.8.4; extra == "dev"
Requires-Dist: h5py>=3.11.0; extra == "dev"
Provides-Extra: examples
Requires-Dist: matplotlib>=3.8.4; extra == "examples"
Requires-Dist: h5py>=3.11.0; extra == "examples"
Dynamic: license-file
